{
	"info": {
		"_postman_id": "c1f2e3d4-b5a6-4c7d-8e9f-0a1b2c3d4e5f",
		"name": "CardioLog API",
		"description": "API documentation for the CardioLog blood pressure tracking application.",
		"schema": "https://schema.getpostman.com/json/collection/v2.1.0/collection.json"
	},
	"item": [
		{
			"name": "Auth",
			"item": [
				{
					"name": "Register",
					"request": {
						"method": "POST",
						"header": [],
						"body": {
							"mode": "raw",
							"raw": "{\n    \"email\": \"test@example.com\",\n    \"password\": \"password123\"\n}",
							"options": {
								"raw": {
									"language": "json"
								}
							}
						},
						"url": {
							"raw": "{{baseUrl}}/api/auth/register",
							"host": [
								"{{baseUrl}}"
							],
							"path": [
								"api",
								"auth",
								"register"
							]
						}
					},
					"response": []
				},
				{
					"name": "Login",
					"event": [
						{
							"listen": "test",
							"script": {
								"exec": [
									"const response = pm.response.json();",
									"if (response.token) {",
									"    pm.environment.set(\"authToken\", response.token);",
									"    pm.environment.set(\"currentUserId\", response.userId);",
									"}"
								],
								"type": "text/javascript"
							}
						}
					],
					"request": {
						"method": "POST",
						"header": [],
						"body": {
							"mode": "raw",
							"raw": "{\n    \"email\": \"test@example.com\",\n    \"password\": \"password123\"\n}",
							"options": {
								"raw": {
									"language": "json"
								}
							}
						},
						"url": {
							"raw": "{{baseUrl}}/api/auth/login",
							"host": [
								"{{baseUrl}}"
							],
							"path": [
								"api",
								"auth",
								"login"
							]
						}
					},
					"response": []
				},
				{
					"name": "Get Current User (Me)",
					"request": {
						"auth": {
							"type": "bearer",
							"bearer": [
								{
									"key": "token",
									"value": "{{authToken}}",
									"type": "string"
								}
							]
						},
						"method": "GET",
						"header": [],
						"url": {
							"raw": "{{baseUrl}}/api/auth/me",
							"host": [
								"{{baseUrl}}"
							],
							"path": [
								"api",
								"auth",
								"me"
							]
						}
					},
					"response": []
				},
				{
					"name": "Update Profile",
					"request": {
						"auth": {
							"type": "bearer",
							"bearer": [
								{
									"key": "token",
									"value": "{{authToken}}",
									"type": "string"
								}
							]
						},
						"method": "PUT",
						"header": [],
						"body": {
							"mode": "raw",
							"raw": "{\n    \"name\": \"John Doe\",\n    \"age\": 30,\n    \"weight\": 75.5,\n    \"height\": 180,\n    \"bloodType\": \"O+\"\n}",
							"options": {
								"raw": {
									"language": "json"
								}
							}
						},
						"url": {
							"raw": "{{baseUrl}}/api/auth/me",
							"host": [
								"{{baseUrl}}"
							],
							"path": [
								"api",
								"auth",
								"me"
							]
						}
					},
					"response": []
				}
			]
		},
		{
			"name": "Profile",
			"item": [
				{
					"name": "Get Profile by ID",
					"request": {
						"method": "GET",
						"header": [],
						"url": {
							"raw": "{{baseUrl}}/api/profile/{{currentUserId}}",
							"host": [
								"{{baseUrl}}"
							],
							"path": [
								"api",
								"profile",
								"{{currentUserId}}"
							]
						}
					},
					"response": []
				}
			]
		},
		{
			"name": "Readings",
			"item": [
				{
					"name": "Add Reading",
					"request": {
						"auth": {
							"type": "bearer",
							"bearer": [
								{
									"key": "token",
									"value": "{{authToken}}",
									"type": "string"
								}
							]
						},
						"method": "POST",
						"header": [],
						"body": {
							"mode": "raw",
							"raw": "{\n    \"systolic\": 120,\n    \"diastolic\": 80,\n    \"pulse\": 72\n}",
							"options": {
								"raw": {
									"language": "json"
								}
							}
						},
						"url": {
							"raw": "{{baseUrl}}/api/readings",
							"host": [
								"{{baseUrl}}"
							],
							"path": [
								"api",
								"readings"
							]
						}
					},
					"response": []
				},
				{
					"name": "Get My Readings",
					"request": {
						"auth": {
							"type": "bearer",
							"bearer": [
								{
									"key": "token",
									"value": "{{authToken}}",
									"type": "string"
								}
							]
						},
						"method": "GET",
						"header": [],
						"url": {
							"raw": "{{baseUrl}}/api/readings/my",
							"host": [
								"{{baseUrl}}"
							],
							"path": [
								"api",
								"readings",
								"my"
							]
						}
					},
					"response": []
				},
				{
					"name": "Get Reading Stats",
					"request": {
						"auth": {
							"type": "bearer",
							"bearer": [
								{
									"key": "token",
									"value": "{{authToken}}",
									"type": "string"
								}
							]
						},
						"method": "GET",
						"header": [],
						"url": {
							"raw": "{{baseUrl}}/api/readings/stats",
							"host": [
								"{{baseUrl}}"
							],
							"path": [
								"api",
								"readings",
								"stats"
							]
						}
					},
					"response": []
				},
				{
					"name": "Delete Reading",
					"request": {
						"auth": {
							"type": "bearer",
							"bearer": [
								{
									"key": "token",
									"value": "{{authToken}}",
									"type": "string"
								}
							]
						},
						"method": "DELETE",
						"header": [],
						"url": {
							"raw": "{{baseUrl}}/api/readings/:id",
							"host": [
								"{{baseUrl}}"
							],
							"path": [
								"api",
								"readings",
								":id"
							],
							"variable": [
								{
									"key": "id",
									"value": "reading_uuid_here"
								}
							]
						}
					},
					"response": []
				}
			]
		}
	],
	"variable": [
		{
			"key": "baseUrl",
			"value": "http://localhost:3000",
			"type": "string"
		},
		{
			"key": "authToken",
			"value": "",
			"type": "string"
		},
		{
			"key": "currentUserId",
			"value": "",
			"type": "string"
		}
	]
}
